{
  "american": [
    "american",
    "mac and cheese"
  ],
  "mexican": [
    "mexican"
  ],
  "italian": [
    "italian"
  ],
  "chinese": [
    "chinese"
  ],
  "japanese": [
    "japanese"
  ],
  "asian fusion": [
    "captain's boil",
    "asian",
    "fusion"
  ],
  "canadian (new)": [
    "canadian",
    "poutine"
  ],
  "mediterranean": [
    "mediterranean"
  ],
  "thai": [
    "thai"
  ],
  "indian": [
    "indian"
  ],
  "vietnamese": [
    "vietnamese"
  ],
  "middle eastern": [
    "middle eastern"
  ],
  "greek": [
    "greek"
  ],
  "korean": [
    "korean"
  ]
}